git_credentials/__init__.py
git_credentials/credentials.py
git_credentials/py.typed
git_credentials-1.0.0.dist-info/LICENSE
git_credentials-1.0.0.dist-info/METADATA
git_credentials-1.0.0.dist-info/WHEEL
git_credentials-1.0.0.dist-info/top_level.txt
git_credentials-1.0.0.dist-info/RECORD
