Metadata-Version: 2.1
Name: git-credentials
Version: 1.0.0
Summary: Simple library to interact with Git Credentials
Home-page: https://github.com/theCapypara/python-git-credentials/
Author: Marco "Capypara" Köpcke
License: MIT
Platform: UNKNOWN
Classifier: Development Status :: 5 - Production/Stable
Classifier: Programming Language :: Python
Classifier: Intended Audience :: Developers
Classifier: License :: OSI Approved :: MIT License
Classifier: Programming Language :: Python :: 3.6
Classifier: Programming Language :: Python :: 3.7
Classifier: Programming Language :: Python :: 3.8
Classifier: Programming Language :: Python :: 3.9
Classifier: Programming Language :: Python :: 3.10
License-File: LICENSE
